[
  {
    "id_pessoas": 295,
    "nome_pessoa": "ADRIANO DE PAULA VERISSIMO JUNIOR",
    "departamento": "GESTAO INTEGRADA ZEMA"
  },
  {
    "id_pessoas": 257,
    "nome_pessoa": "ADRIANO JOSE GUIMARAES",
    "departamento": "TI - ERP"
  },
  {
    "id_pessoas": 318,
    "nome_pessoa": "AIRES FULGENCIO MACHADO",
    "departamento": "FINANCEIRO"
  },
  {
    "id_pessoas": 378,
    "nome_pessoa": "AIRTON CEZARIO DA SILVA JUNIOR",
    "departamento": "LOGISTICA"
  },
  {
    "id_pessoas": 433,
    "nome_pessoa": "ALAERCIO MARTINS JUNIOR",
    "departamento": "TI - SOFTWARE"
  },
  {
    "id_pessoas": 224,
    "nome_pessoa": "ALANA APARECIDA DE ARAUJO CAMPOS",
    "departamento": "RECURSOS HUMANOS"
  },
  {
    "id_pessoas": 2634,
    "nome_pessoa": "ALCIENE FRANCIELLE CAMPOS",
    "departamento": "OPERACOES DE CREDITO"
  },
  {
    "id_pessoas": 617,
    "nome_pessoa": "ALESSANDRA NOGUEIRA FERREIRA",
    "departamento": "CENTRO DE DISTRIBUICAO GERAL"
  },
  {
    "id_pessoas": 310,
    "nome_pessoa": "ALEX DANILO DE PAULO",
    "departamento": "CENTRAL DE QUALIDADE"
  },
  {
    "id_pessoas": 2959,
    "nome_pessoa": "ALEXANDRE RODRIGO BRAGA",
    "departamento": "LOGISTICA"
  },
  {
    "id_pessoas": 461,
    "nome_pessoa": "ALINE DE FATIMA DA SILVA",
    "departamento": "TI - ERP"
  },
  {
    "id_pessoas": 336,
    "nome_pessoa": "ALINE FERNANDA DA SILVA",
    "departamento": "COMPRAS"
  },
  {
    "id_pessoas": 2488,
    "nome_pessoa": "ALINE SANTOS ZAMBROTI",
    "departamento": "ASSESSORIA CONTABIL"
  },
  {
    "id_pessoas": 2865,
    "nome_pessoa": "ALISSON BRUNO DA SILVA",
    "departamento": "PLANEJAMENTO ECONOMICO E FINANCEIRO"
  },
  {
    "id_pessoas": 347,
    "nome_pessoa": "ALVISLENE CRISTINA SOUZA LOPES",
    "departamento": "DEPARTAMENTO PESSOAL"
  },
  {
    "id_pessoas": 2635,
    "nome_pessoa": "AMANDA APARECIDA FERREIRA",
    "departamento": "OPERACOES DE CREDITO"
  },
  {
    "id_pessoas": 388,
    "nome_pessoa": "AMANDA NAJILA MARINS SILVA",
    "departamento": "TI - GERE?NCIA"
  },
  {
    "id_pessoas": 729,
    "nome_pessoa": "AMILTON SOARES DOS SANTOS",
    "departamento": "OBRAS E ENGENHARIA"
  },
  {
    "id_pessoas": 1677,
    "nome_pessoa": "ANA CAROLINA BORGES SILVA",
    "departamento": "OVERHEAD - CONTROLES INTERNOS"
  },
  {
    "id_pessoas": 2866,
    "nome_pessoa": "ANA CAROLINA DE SOUZA COSTA",
    "departamento": "COMPRAS"
  },
  {
    "id_pessoas": 674,
    "nome_pessoa": "ANA CAROLINA FONTES GREGORI",
    "departamento": "OVERHEAD - B.OFF TESOURARIA"
  },
  {
    "id_pessoas": 675,
    "nome_pessoa": "ANA CAROLINA MARQUES ABDO PAIVA",
    "departamento": "OVERHEAD - CONTROLES INTERNOS"
  },
  {
    "id_pessoas": 2008,
    "nome_pessoa": "ANA CAROLINA SILVA RIBEIRO",
    "departamento": "CENTRO DE DISTRIBUICAO GERAL"
  },
  {
    "id_pessoas": 85,
    "nome_pessoa": "ANA CLARA BORGES DA SILVA",
    "departamento": "ATENDIMENTO"
  },
  {
    "id_pessoas": 2636,
    "nome_pessoa": "ANA FLAVIA SILVA LIMA",
    "departamento": "OPERACOES DE CREDITO"
  },
  {
    "id_pessoas": 1919,
    "nome_pessoa": "ANA LAURA DUTRA SILVA",
    "departamento": "FINANCEIRO"
  },
  {
    "id_pessoas": 47,
    "nome_pessoa": "ANA LUIZA MARGARIDA",
    "departamento": "SOLUCOES ECONOMICAS"
  },
  {
    "id_pessoas": 2553,
    "nome_pessoa": "ANA LUIZA VASCONCELOS DE MELO",
    "departamento": "FINANCEIRO"
  },
  {
    "id_pessoas": 2407,
    "nome_pessoa": "ANA PAULA ALVES DE OLIVEIRA",
    "departamento": "MARKETING"
  },
  {
    "id_pessoas": 255,
    "nome_pessoa": "ANA PAULA DA SILVA",
    "departamento": "FINANCEIRO"
  },
  {
    "id_pessoas": 419,
    "nome_pessoa": "ANA TERESA MIGUEL PAROLINI CRUZ",
    "departamento": "MARKETING"
  },
  {
    "id_pessoas": 428,
    "nome_pessoa": "ANA VITORIA FERREIRA MONTANDON",
    "departamento": "AUDITORIA INTERNA"
  },
  {
    "id_pessoas": 342,
    "nome_pessoa": "ANDERSON ADRIANO DE ALMEIDA",
    "departamento": "LOGISTICA"
  },
  {
    "id_pessoas": 443,
    "nome_pessoa": "ANDERSON LUIS DOS REIS",
    "departamento": "TI ERP 2"
  },
  {
    "id_pessoas": 457,
    "nome_pessoa": "ANDERSON OLIVEIRA SILVA",
    "departamento": "AUDITORIA INTERNA"
  },
  {
    "id_pessoas": 2801,
    "nome_pessoa": "ANDERSON SOUZA ALVES",
    "departamento": "LOGISTICA"
  },
  {
    "id_pessoas": 321,
    "nome_pessoa": "ANDRE LUIZ OLIVEIRA DE SA",
    "departamento": "TI - DESENVOLVIMENTO"
  },
  {
    "id_pessoas": 276,
    "nome_pessoa": "ANDREIA ELIANE CUNHA",
    "departamento": "DEPARTAMENTO PESSOAL"
  },
  {
    "id_pessoas": 485,
    "nome_pessoa": "ANDRESSA ARAUJO MACHADO VELASCO",
    "departamento": "TI - CENTRAL DE SERVICOS"
  },
  {
    "id_pessoas": 2411,
    "nome_pessoa": "ANDRESSA CRISTINA MELO CAMPOS",
    "departamento": "OBRAS E ENGENHARIA"
  },
  {
    "id_pessoas": 677,
    "nome_pessoa": "ANDRESSA SILVA MAGALHAES",
    "departamento": "OVERHEAD - CONTROLADORIA"
  },
  {
    "id_pessoas": 2718,
    "nome_pessoa": "ANNE KALYNE DOS REIS MACHADO VAZ",
    "departamento": "OVERHEAD - CONTROLES INTERNOS"
  },
  {
    "id_pessoas": 205,
    "nome_pessoa": "ANTONIO COELHO CIPRIANO",
    "departamento": "LOGISTICA"
  },
  {
    "id_pessoas": 2961,
    "nome_pessoa": "ANTONIO EDISON MARCELINO PEREIRA",
    "departamento": "EXPANSAO (NOVAS FILIAIS)"
  },
  {
    "id_pessoas": 1484,
    "nome_pessoa": "ANTONIO JOSE FELIPE DO NASCIMENTO",
    "departamento": "LOGISTICA"
  },
  {
    "id_pessoas": 432,
    "nome_pessoa": "ANTONIO JOSE MORAES JUNIOR",
    "departamento": "LOGISTICA"
  },
  {
    "id_pessoas": 2802,
    "nome_pessoa": "ANTONIO LUCIANO DA SILVA NASCIMENTO",
    "departamento": "LOGISTICA"
  },
  {
    "id_pessoas": 138,
    "nome_pessoa": "ANTONIO MARCOS DA SILVA",
    "departamento": "LOGISTICA"
  },
  {
    "id_pessoas": 251,
    "nome_pessoa": "ARLENE APARECIDA REZENDE SILVA",
    "departamento": "FINANCEIRO"
  },
  {
    "id_pessoas": 2867,
    "nome_pessoa": "ARTHUR BORGES DE CARVALHO",
    "departamento": "TI - CENTRAL DE SERVICOS"
  },
  {
    "id_pessoas": 2868,
    "nome_pessoa": "ARTHUR HENRIQUE DE OLIVEIRA DE ALMEIDA",
    "departamento": "MARKETING"
  },
  {
    "id_pessoas": 299,
    "nome_pessoa": "ATILA POLYANA DA SILVA",
    "departamento": "CENTRAL DE QUALIDADE"
  },
  {
    "id_pessoas": 243,
    "nome_pessoa": "AUSTRIA MARIA DOS SANTOS",
    "departamento": "LOGISTICA"
  },
  {
    "id_pessoas": 200,
    "nome_pessoa": "BARBARA HELLEN MARCELINO",
    "departamento": "FINANCEIRO"
  },
  {
    "id_pessoas": 2495,
    "nome_pessoa": "BARBARA VITORIA FERREIRA",
    "departamento": "DIRETORIA - DIRETORIA COMERCIAL"
  },
  {
    "id_pessoas": 625,
    "nome_pessoa": "BETANIA ROBERTA GOMES BORGES",
    "departamento": "CREDITO E COBRANCA"
  },
  {
    "id_pessoas": 330,
    "nome_pessoa": "BIANCA FARIA DE PAIVA",
    "departamento": "PLANEJAMENTO ECONOMICO E FINANCEIRO"
  },
  {
    "id_pessoas": 1355,
    "nome_pessoa": "BRUNA CRISTINA ALMEIDA SILVA",
    "departamento": "CENTRO DE DISTRIBUICAO GERAL"
  },
  {
    "id_pessoas": 2074,
    "nome_pessoa": "BRUNA DA SILVA FARIA",
    "departamento": "OVERHEAD - CONTROLADORIA"
  },
  {
    "id_pessoas": 2799,
    "nome_pessoa": "BRUNA LUCAS DE SOUZA INACIO",
    "departamento": "SOLUCOES ECONOMICAS"
  },
  {
    "id_pessoas": 447,
    "nome_pessoa": "BRUNO CASSIANO DIAS",
    "departamento": "JURIDICO"
  },
  {
    "id_pessoas": 219,
    "nome_pessoa": "BRUNO CIPRIANO AUGUSTO",
    "departamento": "TI - ERP"
  },
  {
    "id_pessoas": 372,
    "nome_pessoa": "BRUNO WILLIAM FERREIRA",
    "departamento": "MARKETING"
  },
  {
    "id_pessoas": 628,
    "nome_pessoa": "CAMILA VIEIRA RODRIGUES ALVES",
    "departamento": "CENTRO DE DISTRIBUICAO GERAL"
  },
  {
    "id_pessoas": 196,
    "nome_pessoa": "CARLOS DIMAS SILVA",
    "departamento": "LOGISTICA"
  },
  {
    "id_pessoas": 470,
    "nome_pessoa": "CARLOS EDUARDO RODRIGUES DA SILVA",
    "departamento": "TI - DESENVOLVIMENTO"
  },
  {
    "id_pessoas": 1610,
    "nome_pessoa": "CAROLAINE APARECIDA ALVES",
    "departamento": "TI ERP 2"
  },
  {
    "id_pessoas": 186,
    "nome_pessoa": "CELESTINO DOS SANTOS",
    "departamento": "LOGISTICA"
  },
  {
    "id_pessoas": 605,
    "nome_pessoa": "CIBELY DE FATIMA ALMEIDA",
    "departamento": "SECRETARIA EXECUTIVA"
  },
  {
    "id_pessoas": 394,
    "nome_pessoa": "CICERO ALVES DE SOUZA",
    "departamento": "LOGISTICA"
  },
  {
    "id_pessoas": 2126,
    "nome_pessoa": "CINTHIA HELENA APARECIDA DOS SANTOS",
    "departamento": "CREDITO E COBRANCA"
  },
  {
    "id_pessoas": 491,
    "nome_pessoa": "CLAUDIA BERNADINA BORGES DA SILVA MELO",
    "departamento": "ZEMA FASHION - CD"
  },
  {
    "id_pessoas": 680,
    "nome_pessoa": "CLAUDINELY FERREIRA",
    "departamento": "OVERHEAD - GERENTE 1"
  },
  {
    "id_pessoas": 315,
    "nome_pessoa": "CLEIDE MARA DA COSTA SILVA",
    "departamento": "COMPRAS"
  },
  {
    "id_pessoas": 2351,
    "nome_pessoa": "CLEITON DOS REIS ALVES FILHO",
    "departamento": "FINANCEIRO"
  },
  {
    "id_pessoas": 311,
    "nome_pessoa": "CLEUSA DA PENHA DA SILVA",
    "departamento": "SEGURANCA DO TRABALHO"
  },
  {
    "id_pessoas": 252,
    "nome_pessoa": "CRISTIANE APARECIDA DOS SANTOS",
    "departamento": "LOGISTICA"
  },
  {
    "id_pessoas": 322,
    "nome_pessoa": "CRISTIANE DE OLIVEIRA AVELAR ALVARENGA",
    "departamento": "LOGISTICA"
  },
  {
    "id_pessoas": 681,
    "nome_pessoa": "CRISTIANE FLAVIA DA SILVA",
    "departamento": "OVERHEAD - PROJETOS"
  },
  {
    "id_pessoas": 1061,
    "nome_pessoa": "CRISTINY NAIANE COSTA MARQUES",
    "departamento": "OPERACOES DE CREDITO"
  },
  {
    "id_pessoas": 2644,
    "nome_pessoa": "CYNTHYA HELLEN ASSUNCAO",
    "departamento": "OPERACOES DE CREDITO"
  },
  {
    "id_pessoas": 683,
    "nome_pessoa": "DALILA RODRIGUES PEREIRA SILVA",
    "departamento": "OVERHEAD - PRODUTOS BANCARIOS"
  },
  {
    "id_pessoas": 291,
    "nome_pessoa": "DALMIR VIEIRA SILVA",
    "departamento": "LOGISTICA"
  },
  {
    "id_pessoas": 2688,
    "nome_pessoa": "DANIANE BERNARDES VELASCO SALAZAR",
    "departamento": "RECURSOS HUMANOS"
  },
  {
    "id_pessoas": 456,
    "nome_pessoa": "DANIEL DOS REIS TEODORO FERREIRA",
    "departamento": "TI - ERP"
  },
  {
    "id_pessoas": 211,
    "nome_pessoa": "DANIEL LUCAS DE OLIVEIRA",
    "departamento": "LOGISTICA"
  },
  {
    "id_pessoas": 301,
    "nome_pessoa": "DANIELA CRISTINA DE MORAES",
    "departamento": "LOGISTICA"
  },
  {
    "id_pessoas": 984,
    "nome_pessoa": "DANIELA DE OLIVEIRA RIBEIRO",
    "departamento": "SOLUCOES ECONOMICAS"
  },
  {
    "id_pessoas": 190,
    "nome_pessoa": "DANIELA OLIVEIRA SILVA DO PRADO",
    "departamento": "LOGISTICA"
  },
  {
    "id_pessoas": 631,
    "nome_pessoa": "DANIELA SAMARA DE OLIVEIRA PEREIRA NUNES",
    "departamento": "OPERACOES DE CREDITO"
  },
  {
    "id_pessoas": 2653,
    "nome_pessoa": "DANIELLA MARTINS DOS SANTOS",
    "departamento": "FINANCEIRO"
  },
  {
    "id_pessoas": 685,
    "nome_pessoa": "DANIELLA REZENDE DE CARVALHO",
    "departamento": "OVERHEAD - OUVIDORIA"
  },
  {
    "id_pessoas": 84,
    "nome_pessoa": "DANIELLE CAMILA CAETANO",
    "departamento": "ATENDIMENTO"
  },
  {
    "id_pessoas": 1407,
    "nome_pessoa": "DANIELLY IMARA CARDOSO",
    "departamento": "TRANSPORTE"
  },
  {
    "id_pessoas": 474,
    "nome_pessoa": "DANILION SILVA DO NASCIMENTO",
    "departamento": "LOGISTICA"
  },
  {
    "id_pessoas": 686,
    "nome_pessoa": "DANILO DE ANDRADE CARVALHO",
    "departamento": "OVERHEAD - TI"
  },
  {
    "id_pessoas": 226,
    "nome_pessoa": "DANILO HENRIQUE SILVA DIAS",
    "departamento": "TI - SOFTWARE"
  },
  {
    "id_pessoas": 2717,
    "nome_pessoa": "DARIO OLIVEIRA DA SILVA NETO",
    "departamento": "TI ERP 2"
  },
  {
    "id_pessoas": 606,
    "nome_pessoa": "DAYANE CRISTINA SILVA",
    "departamento": "CENTRO DE DISTRIBUICAO GERAL"
  },
  {
    "id_pessoas": 2313,
    "nome_pessoa": "DEBORA EDUARDA ABADIA SILVA",
    "departamento": "CENTRO DE DISTRIBUICAO GERAL"
  },
  {
    "id_pessoas": 1532,
    "nome_pessoa": "DEBORAH DANTAS CARDOSO",
    "departamento": "OVERHEAD - PRICE"
  },
  {
    "id_pessoas": 296,
    "nome_pessoa": "DENILSON HENRIQUE CARNEIRO DA SILVA",
    "departamento": "TI - CENTRAL DE SERVICOS"
  },
  {
    "id_pessoas": 133,
    "nome_pessoa": "DENISE MARTINS SANTOS",
    "departamento": "LOGISTICA"
  },
  {
    "id_pessoas": 365,
    "nome_pessoa": "DENIZE DE FATIMA MORAIS",
    "departamento": "ASSESSORIA FISCAL"
  },
  {
    "id_pessoas": 632,
    "nome_pessoa": "DEYSIENE PAULA RODRIGUES",
    "departamento": "CREDITO E COBRANCA"
  },
  {
    "id_pessoas": 188,
    "nome_pessoa": "DIEGO HENRIQUE DE ALMEIDA PEREIRA",
    "departamento": "TI - CENTRAL DE SERVICOS"
  },
  {
    "id_pessoas": 633,
    "nome_pessoa": "DIESSYCA TEODORO MARTINS",
    "departamento": "OPERACOES DE CREDITO"
  },
  {
    "id_pessoas": 413,
    "nome_pessoa": "DILERMANO BARCELOS SANTOS",
    "departamento": "LOGISTICA"
  },
  {
    "id_pessoas": 1674,
    "nome_pessoa": "DOUGLAS INACIO FERREIRA",
    "departamento": "OVERHEAD - VENDAS DIGITAIS"
  },
  {
    "id_pessoas": 423,
    "nome_pessoa": "DOUGLAS XAVIER RODRIGUES",
    "departamento": "TI ERP 2"
  },
  {
    "id_pessoas": 2831,
    "nome_pessoa": "EDILSON GOMES DE SOUZA",
    "departamento": "LOGISTICA"
  },
  {
    "id_pessoas": 132,
    "nome_pessoa": "EDIR PEREIRA DE MELO",
    "departamento": "TRANSPORTE"
  },
  {
    "id_pessoas": 2989,
    "nome_pessoa": "EDSON SANTOS DA CRUZ",
    "departamento": "LOGISTICA"
  },
  {
    "id_pessoas": 406,
    "nome_pessoa": "EDUARDO GOMES DE ARAUJO",
    "departamento": "LOGISTICA"
  },
  {
    "id_pessoas": 195,
    "nome_pessoa": "EDVALDO APARECIDO MENEZES",
    "departamento": "LOGISTICA"
  },
  {
    "id_pessoas": 947,
    "nome_pessoa": "ELAINE MARIA DOS SANTOS",
    "departamento": "JURIDICO"
  },
  {
    "id_pessoas": 290,
    "nome_pessoa": "ELENILDES MARINHO LEMES",
    "departamento": "MANUTENCAO 2"
  },
  {
    "id_pessoas": 1789,
    "nome_pessoa": "ELIANE OLEGARIO GOLARTT",
    "departamento": "RECURSOS HUMANOS"
  },
  {
    "id_pessoas": 635,
    "nome_pessoa": "ELISANGELA MARCIA DE SOUZA GOULART",
    "departamento": "CREDITO E COBRANCA"
  },
  {
    "id_pessoas": 112,
    "nome_pessoa": "ELISETY MARCIA TEIXEIRA",
    "departamento": "ADMINISTRACAO CONCESSIONARIA"
  },
  {
    "id_pessoas": 302,
    "nome_pessoa": "ELIZABETE SOARES DOS REIS",
    "departamento": "LOGISTICA"
  },
  {
    "id_pessoas": 240,
    "nome_pessoa": "EMY ASSUNCAO",
    "departamento": "GESTAO INTEGRADA ZEMA"
  },
  {
    "id_pessoas": 1985,
    "nome_pessoa": "ENZO AFIF OLEGARIO FATTAH",
    "departamento": "TI - DESENVOLVIMENTO"
  },
  {
    "id_pessoas": 636,
    "nome_pessoa": "ERICA ABADIA DA SILVA",
    "departamento": "CREDITO E COBRANCA"
  },
  {
    "id_pessoas": 1621,
    "nome_pessoa": "ERIKA CRISTINA DE MENEZES",
    "departamento": "OVERHEAD - CONTROLADORIA"
  },
  {
    "id_pessoas": 2706,
    "nome_pessoa": "EZEQUIEL DEIVID BRUNO",
    "departamento": "TI - ERP"
  },
  {
    "id_pessoas": 487,
    "nome_pessoa": "FABIANA CRISTINA DE SOUZA",
    "departamento": "TI ERP 2"
  },
  {
    "id_pessoas": 223,
    "nome_pessoa": "FABIO SEBASTIAO FERREIRA",
    "departamento": "TI - SOFTWARE"
  },
  {
    "id_pessoas": 159,
    "nome_pessoa": "FABRICIO SABINO CUSTODIO",
    "departamento": "GER.COM.04"
  },
  {
    "id_pessoas": 2105,
    "nome_pessoa": "FERNANDA ALEXANDRE DE PAULA",
    "departamento": "CENTRO DE DISTRIBUICAO GERAL"
  },
  {
    "id_pessoas": 1932,
    "nome_pessoa": "FERNANDA SARA DA SILVA",
    "departamento": "SOLUCOES ECONOMICAS"
  },
  {
    "id_pessoas": 2146,
    "nome_pessoa": "FERNANDA SILVA COSTA",
    "departamento": "ATENDIMENTO"
  },
  {
    "id_pessoas": 306,
    "nome_pessoa": "FLAVIA CRISTINA GOULART",
    "departamento": "ASSESSORIA CONTABIL"
  },
  {
    "id_pessoas": 691,
    "nome_pessoa": "FLORENCA OLIMPIA DE CAMARGOS RIOS",
    "departamento": "OVERHEAD - B.OFF TESOURARIA"
  },
  {
    "id_pessoas": 1060,
    "nome_pessoa": "FLORENCE CRISTINA ROSA",
    "departamento": "MARKETING"
  },
  {
    "id_pessoas": 335,
    "nome_pessoa": "FLORENCE ISABELA DE OLIVEIRA RUFINO",
    "departamento": "ASSESSORIA FISCAL"
  },
  {
    "id_pessoas": 249,
    "nome_pessoa": "FRANCIELE DE LIMA PERES",
    "departamento": "AUDITORIA INTERNA"
  },
  {
    "id_pessoas": 692,
    "nome_pessoa": "FRANCIELLY NATHALIA DE SA",
    "departamento": "OVERHEAD - PRICE"
  },
  {
    "id_pessoas": 2899,
    "nome_pessoa": "FRANCIELLY VERISSIMO CARNEIRO BORGES",
    "departamento": "FINANCEIRO"
  },
  {
    "id_pessoas": 1976,
    "nome_pessoa": "FRANCYELE NAYARA ALVES DE AGUIAR",
    "departamento": "OVERHEAD - CONTROLADORIA"
  },
  {
    "id_pessoas": 2408,
    "nome_pessoa": "GABRIEL ANTHONY BOTELHO",
    "departamento": "TI - DESENVOLVIMENTO"
  },
  {
    "id_pessoas": 2768,
    "nome_pessoa": "GABRIEL BORGES COUTO",
    "departamento": "DIRETOR ADMINISTRATIVO FINANCEIRO"
  },
  {
    "id_pessoas": 1503,
    "nome_pessoa": "GABRIEL FILIPE DA CUNHA IZA",
    "departamento": "OPERACOES DE CREDITO"
  },
  {
    "id_pessoas": 2377,
    "nome_pessoa": "GABRIEL HENRIQUE DE PAULA",
    "departamento": "ARQUIVO/CORRESPONDENCIA"
  },
  {
    "id_pessoas": 1662,
    "nome_pessoa": "GABRIEL HENRIQUE JUSSELINO RAMOS",
    "departamento": "SOLUCOES ECONOMICAS"
  },
  {
    "id_pessoas": 1791,
    "nome_pessoa": "GABRIEL RESENDE RODRIGUES ORCAY",
    "departamento": "TI - ERP"
  },
  {
    "id_pessoas": 152,
    "nome_pessoa": "GABRIELA DE REZENDE SANTOS",
    "departamento": "DEPARTAMENTO PESSOAL"
  },
  {
    "id_pessoas": 639,
    "nome_pessoa": "GABRIELA LUZIA MARQUES SILVA",
    "departamento": "CENTRO DE DISTRIBUICAO GERAL"
  },
  {
    "id_pessoas": 1790,
    "nome_pessoa": "GABRIELLA NEVES PEREIRA",
    "departamento": "ASSESSORIA CONTABIL"
  },
  {
    "id_pessoas": 440,
    "nome_pessoa": "GABRIELLA OLIVEIRA ARANTES COELHO",
    "departamento": "RECURSOS HUMANOS"
  },
  {
    "id_pessoas": 2991,
    "nome_pessoa": "GEOVANA LARA MARCELINO GOMES",
    "departamento": "CENTRO DE DISTRIBUICAO GERAL"
  },
  {
    "id_pessoas": 2293,
    "nome_pessoa": "GERMANO DIAS REZENDE PEREIRA",
    "departamento": "TI ERP 2"
  },
  {
    "id_pessoas": 1675,
    "nome_pessoa": "GERMANO FERREIRA",
    "departamento": "OVERHEAD - VENDAS DIGITAIS"
  },
  {
    "id_pessoas": 2869,
    "nome_pessoa": "GILDA APARECIDA DA SILVA",
    "departamento": "ASSESSORIA CONTABIL"
  },
  {
    "id_pessoas": 221,
    "nome_pessoa": "GILSON EUGENIO DA SILVA",
    "departamento": "LOGISTICA"
  },
  {
    "id_pessoas": 1920,
    "nome_pessoa": "GIOVANA VALERIANO TAMBORRINO",
    "departamento": "FINANCEIRO"
  },
  {
    "id_pessoas": 1643,
    "nome_pessoa": "GIOVANE OTAVIO SILVA",
    "departamento": "MARKETING"
  },
  {
    "id_pessoas": 2127,
    "nome_pessoa": "GIOVANNA KELLY PEREIRA",
    "departamento": "CENTRO DE DISTRIBUICAO GERAL"
  },
  {
    "id_pessoas": 2754,
    "nome_pessoa": "GISELLE CASSIANA DA SILVA",
    "departamento": "CREDITO E COBRANCA"
  },
  {
    "id_pessoas": 232,
    "nome_pessoa": "GLAUCIA CRISTINE BORGES RUFINO",
    "departamento": "AUDITORIA INTERNA"
  },
  {
    "id_pessoas": 155,
    "nome_pessoa": "GLORIA PINHEIRO DE CASTRO SANTOS",
    "departamento": "MANUTENCAO 2"
  },
  {
    "id_pessoas": 2492,
    "nome_pessoa": "GRACIELE CRISTINA CARMO",
    "departamento": "CREDITO E COBRANCA"
  },
  {
    "id_pessoas": 1676,
    "nome_pessoa": "GRAZIELLA NEVES PEREIRA",
    "departamento": "ADMINISTRATIVO GERAL"
  },
  {
    "id_pessoas": 2652,
    "nome_pessoa": "GREICE KELY SOARES PAIXAO",
    "departamento": "SOLUCOES ECONOMICAS"
  },
  {
    "id_pessoas": 2084,
    "nome_pessoa": "GUILHERME AUGUSTO BORGES PINHEIRO JUNIOR",
    "departamento": "TI ERP 2"
  },
  {
    "id_pessoas": 731,
    "nome_pessoa": "GUILHERME DE ALCANTARA MACHADO",
    "departamento": "TI - DESENVOLVIMENTO"
  },
  {
    "id_pessoas": 509,
    "nome_pessoa": "GUSTAVO COSTA BELMIRO",
    "departamento": "E-COMMERCE"
  },
  {
    "id_pessoas": 476,
    "nome_pessoa": "GUSTAVO DA SILVA",
    "departamento": "LOGISTICA"
  },
  {
    "id_pessoas": 462,
    "nome_pessoa": "GUSTAVO DA SILVA RIBEIRO",
    "departamento": "LOGISTICA"
  },
  {
    "id_pessoas": 1529,
    "nome_pessoa": "GUSTAVO HENRIQUE SILVA BORGES",
    "departamento": "TI ERP 2"
  },
  {
    "id_pessoas": 294,
    "nome_pessoa": "GUSTAVO RAFAEL DE ARAUJO SOUSA",
    "departamento": "TI - ERP"
  },
  {
    "id_pessoas": 642,
    "nome_pessoa": "GYOVANA RAISSA DOS REIS PAIXAO FERNANDES",
    "departamento": "OPERACOES DE CREDITO"
  },
  {
    "id_pessoas": 187,
    "nome_pessoa": "HERIBERTO MECENERO FILHO",
    "departamento": "TI - ERP"
  },
  {
    "id_pessoas": 2631,
    "nome_pessoa": "HIZIELE HELENA OLIVEIRA GOMES ALVES",
    "departamento": "ASSESSORIA CONTABIL"
  },
  {
    "id_pessoas": 282,
    "nome_pessoa": "HOSANDIRO AUGUSTO BARBOSA",
    "departamento": "TI - ERP"
  },
  {
    "id_pessoas": 2870,
    "nome_pessoa": "HUGO ADRIANO DE OLIVEIRA",
    "departamento": "MARKETING"
  },
  {
    "id_pessoas": 390,
    "nome_pessoa": "HUGO HENRIQUE BARCELOS",
    "departamento": "ASSESSORIA FISCAL"
  },
  {
    "id_pessoas": 1936,
    "nome_pessoa": "HUGO MARLON CARVALHO RODRIGUES",
    "departamento": "TI - ERP"
  },
  {
    "id_pessoas": 503,
    "nome_pessoa": "HUGO TAVARES REIS",
    "departamento": "TI - ERP"
  },
  {
    "id_pessoas": 361,
    "nome_pessoa": "ILZA APARECIDA BENEDICTO",
    "departamento": "ASSESSORIA CONTABIL"
  },
  {
    "id_pessoas": 2148,
    "nome_pessoa": "IRANILDO MOURA SOUSA",
    "departamento": "LOGISTICA"
  },
  {
    "id_pessoas": 2753,
    "nome_pessoa": "ISABELLY FERNANDA MENDES",
    "departamento": "E-COMMERCE"
  },
  {
    "id_pessoas": 546,
    "nome_pessoa": "ISADORA APARECIDA FIGUEREDO",
    "departamento": "OBRAS E ENGENHARIA"
  },
  {
    "id_pessoas": 697,
    "nome_pessoa": "IUGUIR DE AZEVEDO RABELO",
    "departamento": "OVERHEAD - ADMINISTRATIVO"
  },
  {
    "id_pessoas": 931,
    "nome_pessoa": "IZABEL CRISTINA DE CASTRO SILVA",
    "departamento": "COMPRAS"
  },
  {
    "id_pessoas": 236,
    "nome_pessoa": "IZABELLA DIAS SOARES",
    "departamento": "JURIDICO"
  },
  {
    "id_pessoas": 723,
    "nome_pessoa": "IZABELLA FERREIRA SILVA",
    "departamento": "ADMINISTRATIVO GERAL"
  },
  {
    "id_pessoas": 374,
    "nome_pessoa": "JACIARA RIBEIRO DE MORAIS",
    "departamento": "RECURSOS HUMANOS"
  },
  {
    "id_pessoas": 300,
    "nome_pessoa": "JACKSON ARAUJO DE LIMA",
    "departamento": "LOGISTICA"
  },
  {
    "id_pessoas": 332,
    "nome_pessoa": "JAILSON OLIVEIRA SILVA",
    "departamento": "LOGISTICA"
  },
  {
    "id_pessoas": 164,
    "nome_pessoa": "JANAINA CARNEIRO LEMOS",
    "departamento": "CENTRAL DE QUALIDADE"
  },
  {
    "id_pessoas": 204,
    "nome_pessoa": "JANETE APARECIDA GOMES",
    "departamento": "CENTRAL DE QUALIDADE"
  },
  {
    "id_pessoas": 430,
    "nome_pessoa": "JAQUELINE APARECIDA DE OLIVEIRA",
    "departamento": "ASSESSORIA CONTABIL"
  },
  {
    "id_pessoas": 161,
    "nome_pessoa": "JAQUELINE APARECIDA LEMOS",
    "departamento": "PLANEJAMENTO ECONOMICO E FINANCEIRO"
  },
  {
    "id_pessoas": 137,
    "nome_pessoa": "JEAN PAUL DE MORAES SIMOES",
    "departamento": "LOGISTICA"
  },
  {
    "id_pessoas": 260,
    "nome_pessoa": "JEFERSON AUGUSTO DA SILVA OLIVEIRA",
    "departamento": "LOGISTICA"
  },
  {
    "id_pessoas": 395,
    "nome_pessoa": "JEFFERSON DA SILVA FEITOZA",
    "departamento": "LOGISTICA"
  },
  {
    "id_pessoas": 2654,
    "nome_pessoa": "JEFFERSON MORAES SIMOES",
    "departamento": "LOGISTICA"
  },
  {
    "id_pessoas": 1444,
    "nome_pessoa": "JEILSON MARCELINO CARVALHO SILVA",
    "departamento": "LOGISTICA"
  },
  {
    "id_pessoas": 514,
    "nome_pessoa": "JESSICA FLORENCIA LACERDA BORGES",
    "departamento": "E-COMMERCE"
  },
  {
    "id_pessoas": 78,
    "nome_pessoa": "JESSICA KEILA DOS SANTOS SOUZA",
    "departamento": "ATENDIMENTO"
  },
  {
    "id_pessoas": 2518,
    "nome_pessoa": "JESSICA LUANA FERREIRA",
    "departamento": "DEPARTAMENTO PESSOAL"
  },
  {
    "id_pessoas": 392,
    "nome_pessoa": "JHONY HENRIQUE DE CARVALHO",
    "departamento": "LOGISTICA"
  },
  {
    "id_pessoas": 2493,
    "nome_pessoa": "JOAO PAULO BERNARDES",
    "departamento": "OVERHEAD - PRODUTOS BANCARIOS"
  },
  {
    "id_pessoas": 1579,
    "nome_pessoa": "JOAO PAULO FERREIRA SILVA",
    "departamento": "MARKETING"
  },
  {
    "id_pessoas": 2294,
    "nome_pessoa": "JOAO PEDRO FERNANDES DE LIMA",
    "departamento": "MARKETING"
  },
  {
    "id_pessoas": 169,
    "nome_pessoa": "JOAO SERAFIM RIBEIRO",
    "departamento": "MANUTENCAO 2"
  },
  {
    "id_pessoas": 455,
    "nome_pessoa": "JOAO VITOR DUARTE DA SILVA",
    "departamento": "TI ERP 2"
  },
  {
    "id_pessoas": 2874,
    "nome_pessoa": "JOAO VITOR SANTOS DA SILVA",
    "departamento": "ASSESSORIA CONTABIL"
  },
  {
    "id_pessoas": 86,
    "nome_pessoa": "JOHNATA HENRIQUE SILVA",
    "departamento": "COMERCIAL BACKOFFICE"
  },
  {
    "id_pessoas": 2471,
    "nome_pessoa": "JOSE AILTON CORDEIRO DA SILVA",
    "departamento": "LOGISTICA"
  },
  {
    "id_pessoas": 344,
    "nome_pessoa": "JOSE ALECKSON MORAIS DE OLIVEIRA",
    "departamento": "LOGISTICA"
  },
  {
    "id_pessoas": 285,
    "nome_pessoa": "JOSE ANTONIO DUARTE",
    "departamento": "LOGISTICA"
  },
  {
    "id_pessoas": 549,
    "nome_pessoa": "JOSE APARECIDO NOGUEIRA DE SOUZA",
    "departamento": "OBRAS E ENGENHARIA"
  },
  {
    "id_pessoas": 178,
    "nome_pessoa": "JOSE FRANCISCO DOS SANTOS",
    "departamento": "LOGISTICA"
  },
  {
    "id_pessoas": 699,
    "nome_pessoa": "JOSE JOAQUIM DE OLIVEIRA JUNIOR",
    "departamento": "DIRETORIA - DIRETORIA FINANCEIRA"
  },
  {
    "id_pessoas": 407,
    "nome_pessoa": "JOSE RODRIGUES DA CRUZ",
    "departamento": "LOGISTICA"
  },
  {
    "id_pessoas": 2987,
    "nome_pessoa": "JOSELAINE GARCIA ALVARENGA",
    "departamento": "GESTAO INTEGRADA ZEMA"
  },
  {
    "id_pessoas": 77,
    "nome_pessoa": "JOSIANE STEFANI BORGES DE OLIVEIRA",
    "departamento": "ATENDIMENTO"
  },
  {
    "id_pessoas": 700,
    "nome_pessoa": "JOUBERT WARLEISON CARNEIRO",
    "departamento": "OVERHEAD - CONTROLADORIA"
  },
  {
    "id_pessoas": 468,
    "nome_pessoa": "JOYCE MARQUES DOS REIS LEMOS",
    "departamento": "RECURSOS HUMANOS"
  },
  {
    "id_pessoas": 192,
    "nome_pessoa": "JUDITH MARTINS",
    "departamento": "ASSESSORIA FISCAL"
  },
  {
    "id_pessoas": 2205,
    "nome_pessoa": "JULIA BEATRIZ SILVA",
    "departamento": "OVERHEAD - ADMINISTRATIVO"
  },
  {
    "id_pessoas": 702,
    "nome_pessoa": "JULIANA EUGENIA DA SILVA ANDRADE",
    "departamento": "OVERHEAD - B.OFF TESOURARIA"
  },
  {
    "id_pessoas": 250,
    "nome_pessoa": "JULIANA RAQUEL DE OLIVEIRA",
    "departamento": "DEPARTAMENTO PESSOAL"
  },
  {
    "id_pessoas": 646,
    "nome_pessoa": "JULIANE DE FATIMA OLIVEIRA DA SILVA",
    "departamento": "CENTRO DE DISTRIBUICAO GERAL"
  },
  {
    "id_pessoas": 2633,
    "nome_pessoa": "KAMILLA ALVES DOS REIS",
    "departamento": "OPERACOES DE CREDITO"
  },
  {
    "id_pessoas": 341,
    "nome_pessoa": "KATIA DE FATIMA DE OLIVEIRA",
    "departamento": "FINANCEIRO"
  },
  {
    "id_pessoas": 581,
    "nome_pessoa": "KEILA CRISTINA CANDIDO",
    "departamento": "ADMINISTRACAO CONCES."
  },
  {
    "id_pessoas": 94,
    "nome_pessoa": "KEILA CRISTINA DA SILVA",
    "departamento": "ATENDIMENTO"
  },
  {
    "id_pessoas": 454,
    "nome_pessoa": "KEILA CRISTINA MORAIS LIMA",
    "departamento": "CENTRAL DE QUALIDADE"
  },
  {
    "id_pessoas": 225,
    "nome_pessoa": "KELLEN CRISTINA NOGUEIRA",
    "departamento": "FINANCEIRO"
  },
  {
    "id_pessoas": 1263,
    "nome_pessoa": "KELY CURTO BERNARDO",
    "departamento": "COMERCIAL BACKOFFICE"
  },
  {
    "id_pessoas": 143,
    "nome_pessoa": "LAENA KAREN DE OLIVEIRA",
    "departamento": "FINANCEIRO"
  },
  {
    "id_pessoas": 2703,
    "nome_pessoa": "LAILANIA NATALIA LIMA",
    "departamento": "ATENDIMENTO"
  },
  {
    "id_pessoas": 705,
    "nome_pessoa": "LARISSA ELLEN ANIBAL",
    "departamento": "OVERHEAD - AUDITORIA INTERNA"
  },
  {
    "id_pessoas": 1362,
    "nome_pessoa": "LARISSA MARIANO LEMOS TEIXEIRA",
    "departamento": "E-COMMERCE"
  },
  {
    "id_pessoas": 2626,
    "nome_pessoa": "LARISSA MENDES DA SILVA",
    "departamento": "FINANCEIRO"
  },
  {
    "id_pessoas": 1021,
    "nome_pessoa": "LARISSA SANTOS MARTINS",
    "departamento": "RECURSOS HUMANOS"
  },
  {
    "id_pessoas": 2967,
    "nome_pessoa": "LAYANE CRISTINA ARAUJO TAVARES",
    "departamento": "CENTRO DE DISTRIBUICAO GERAL"
  },
  {
    "id_pessoas": 408,
    "nome_pessoa": "LEANDRO DE SOUZA NUNES",
    "departamento": "LOGISTICA"
  },
  {
    "id_pessoas": 158,
    "nome_pessoa": "LEIDIANE APARECIDA DA SILVA",
    "departamento": "FINANCEIRO"
  },
  {
    "id_pessoas": 2800,
    "nome_pessoa": "LEILIANE PATRICIA DE MENEZES",
    "departamento": "SOLUCOES ECONOMICAS"
  },
  {
    "id_pessoas": 2803,
    "nome_pessoa": "LENILSON BARBOZA DE PAULA",
    "departamento": "LOGISTICA"
  },
  {
    "id_pessoas": 104,
    "nome_pessoa": "LEOMAR GARCIA DA SILVA",
    "departamento": "OVERHEAD - Administrativo Geral"
  },
  {
    "id_pessoas": 83,
    "nome_pessoa": "LEONARDO HENRIQUE RESENDE SILVA",
    "departamento": "CADASTRO"
  },
  {
    "id_pessoas": 1465,
    "nome_pessoa": "LETICIA LEIDIANE ALVES CARNEIRO",
    "departamento": "OVERHEAD - VENDAS DIGITAIS"
  },
  {
    "id_pessoas": 283,
    "nome_pessoa": "LINDOMAR DA SILVA CAMELO",
    "departamento": "LOGISTICA"
  },
  {
    "id_pessoas": 339,
    "nome_pessoa": "LORENA APARECIDA MACIEL DE SOUZA",
    "departamento": "COMPRAS"
  },
  {
    "id_pessoas": 494,
    "nome_pessoa": "LORENA DE CAMARGO VIANA MOREIRA",
    "departamento": "AUDITORIA INTERNA"
  },
  {
    "id_pessoas": 2517,
    "nome_pessoa": "LORENA DE LOURDES PEREIRA VALERIANO",
    "departamento": "FINANCEIRO"
  },
  {
    "id_pessoas": 2567,
    "nome_pessoa": "LORRAINE MARTINS RODRIGUES DA SILVA",
    "departamento": "ARQUIVO/CORRESPONDENCIA"
  },
  {
    "id_pessoas": 707,
    "nome_pessoa": "LUANA BORGES MELO",
    "departamento": "OVERHEAD - ADMINISTRATIVO"
  },
  {
    "id_pessoas": 418,
    "nome_pessoa": "LUANA NATALIA FERREIRA",
    "departamento": "COMPRAS"
  },
  {
    "id_pessoas": 1687,
    "nome_pessoa": "LUANA TRIGUEIRO RAMOS DA SILVA",
    "departamento": "RECURSOS HUMANOS"
  },
  {
    "id_pessoas": 1922,
    "nome_pessoa": "LUCAS EDUARDO GONCALVES",
    "departamento": "TI GERENCIA GERAL"
  },
  {
    "id_pessoas": 490,
    "nome_pessoa": "LUCAS GABRIEL OLIVEIRA DA SILVA",
    "departamento": "TI ERP 2"
  },
  {
    "id_pessoas": 2871,
    "nome_pessoa": "LUCAS HENRIQUE CARVALHO MARQUES",
    "departamento": "COMUNICACOES"
  },
  {
    "id_pessoas": 2872,
    "nome_pessoa": "LUCAS NATAN FERREIRA",
    "departamento": "ASSESSORIA FISCAL"
  },
  {
    "id_pessoas": 145,
    "nome_pessoa": "LUCAS SILVA RESENDE",
    "departamento": "GESTAO INTEGRADA ZEMA"
  },
  {
    "id_pessoas": 180,
    "nome_pessoa": "LUCAS VIEIRA CAIXETA",
    "departamento": "FINANCEIRO"
  },
  {
    "id_pessoas": 2128,
    "nome_pessoa": "LUCIENE CRISTINA DA SILVA",
    "departamento": "CENTRO DE DISTRIBUICAO GERAL"
  },
  {
    "id_pessoas": 2489,
    "nome_pessoa": "LUCIMARA ABADIA DE ARAUJO COSTA",
    "departamento": "RECURSOS HUMANOS"
  },
  {
    "id_pessoas": 939,
    "nome_pessoa": "LUDIMILA DE FATIMA MENEZES",
    "departamento": "CENTRO DE DISTRIBUICAO GERAL"
  },
  {
    "id_pessoas": 356,
    "nome_pessoa": "LUDMYLLA PONCEANO DOS SANTOS",
    "departamento": "RECURSOS HUMANOS"
  },
  {
    "id_pessoas": 346,
    "nome_pessoa": "LUIZ CELSO DE CASTRO",
    "departamento": "ARQUIVO/CORRESPONDENCIA"
  },
  {
    "id_pessoas": 1664,
    "nome_pessoa": "LUIZ FELIPE DA SILVA DOMINGOS",
    "departamento": "PLANEJAMENTO ECONOMICO E FINANCEIRO"
  },
  {
    "id_pessoas": 217,
    "nome_pessoa": "LUIZ FERNANDO DE MAGALHAES",
    "departamento": "LOGISTICA"
  },
  {
    "id_pessoas": 2072,
    "nome_pessoa": "LUIZ FERNANDO MENDES DE OLIVEIRA",
    "departamento": "CENTRO DE DISTRIBUICAO GERAL"
  },
  {
    "id_pessoas": 1040,
    "nome_pessoa": "LUIZ JAMERSON DOS SANTOS SILVA",
    "departamento": "LOGISTICA"
  },
  {
    "id_pessoas": 431,
    "nome_pessoa": "LUIZ PAULO DE SOUZA",
    "departamento": "CENTRAL DE QUALIDADE"
  },
  {
    "id_pessoas": 403,
    "nome_pessoa": "MAILSON RODRIGO DE LIMA",
    "departamento": "TI - CENTRAL DE SERVICOS"
  },
  {
    "id_pessoas": 2833,
    "nome_pessoa": "MAISA GONCALVES VARGAS",
    "departamento": "OPERACOES DE CREDITO"
  },
  {
    "id_pessoas": 284,
    "nome_pessoa": "MANOEL APRIGIO DO NASCIMENTO",
    "departamento": "LOGISTICA"
  },
  {
    "id_pessoas": 170,
    "nome_pessoa": "MARCELO ANDREIA BORGES",
    "departamento": "COMPRAS"
  },
  {
    "id_pessoas": 268,
    "nome_pessoa": "MARCOS ROBERTO DA SILVA",
    "departamento": "LOGISTICA"
  },
  {
    "id_pessoas": 1108,
    "nome_pessoa": "MARCUS VINICIUS RIBEIRO ANDRADE",
    "departamento": "MARKETING"
  },
  {
    "id_pessoas": 220,
    "nome_pessoa": "MARIA APARECIDA DE OLIVEIRA",
    "departamento": "MANUTENCAO 2"
  },
  {
    "id_pessoas": 2762,
    "nome_pessoa": "MARIA APARECIDA DUARTE",
    "departamento": "RECURSOS HUMANOS"
  },
  {
    "id_pessoas": 153,
    "nome_pessoa": "MARIA CRISTIANE ENY BORGES",
    "departamento": "TI ERP 2"
  },
  {
    "id_pessoas": 2240,
    "nome_pessoa": "MARIA EDUARDA DUTRA",
    "departamento": "ARQUIVO/CORRESPONDENCIA"
  },
  {
    "id_pessoas": 2418,
    "nome_pessoa": "MARIA EDUARDA NESRALA VALE CASTILHO",
    "departamento": "CREDITO E COBRANCA"
  },
  {
    "id_pessoas": 1619,
    "nome_pessoa": "MARIA GABRIELA LIMA DA SILVA",
    "departamento": "COMPRAS"
  },
  {
    "id_pessoas": 2487,
    "nome_pessoa": "MARIA LAURA ALVES PEREIRA",
    "departamento": "ATENDIMENTO"
  },
  {
    "id_pessoas": 2897,
    "nome_pessoa": "MARIA LUIZA DA SILVA VALERIANO",
    "departamento": "RISCO"
  },
  {
    "id_pessoas": 128,
    "nome_pessoa": "MARIA VANILDA TEIXEIRA",
    "departamento": "JURIDICO"
  },
  {
    "id_pessoas": 1680,
    "nome_pessoa": "MARIANA APARECIDA BIANCHINI",
    "departamento": "ASSESSORIA CONTABIL"
  },
  {
    "id_pessoas": 1829,
    "nome_pessoa": "MARIANA RIOS LUZ",
    "departamento": "NOVOS CLIENTES"
  },
  {
    "id_pessoas": 2632,
    "nome_pessoa": "MARIANE SEVERO FERREIRA",
    "departamento": "TI - ERP"
  },
  {
    "id_pessoas": 146,
    "nome_pessoa": "MARIELEN DA COSTA SANTOS",
    "departamento": "DEPARTAMENTO PESSOAL"
  },
  {
    "id_pessoas": 198,
    "nome_pessoa": "MARILIA GRACIELA REZENDE CERAJOLI",
    "departamento": "DEPARTAMENTO PESSOAL"
  },
  {
    "id_pessoas": 657,
    "nome_pessoa": "MARIO APARECIDO SALVADOR",
    "departamento": "CREDITO E COBRANCA"
  },
  {
    "id_pessoas": 261,
    "nome_pessoa": "MARQUES DE MELO FILHO",
    "departamento": "TI - DESENVOLVIMENTO"
  },
  {
    "id_pessoas": 387,
    "nome_pessoa": "MARY ANGELINA DE OLIVEIRA",
    "departamento": "FINANCEIRO"
  },
  {
    "id_pessoas": 2832,
    "nome_pessoa": "MATEUS GOMES DA SILVA",
    "departamento": "LOGISTICA"
  },
  {
    "id_pessoas": 1987,
    "nome_pessoa": "MATEUS HENRIQUE ALVES FERREIRA",
    "departamento": "TI - ERP"
  },
  {
    "id_pessoas": 551,
    "nome_pessoa": "MATHEUS CONTATO DE MENEZES",
    "departamento": "OBRAS E ENGENHARIA"
  },
  {
    "id_pessoas": 481,
    "nome_pessoa": "MATHEUS HENRIQUE DE OLIVEIRA COSTA",
    "departamento": "MARKETING"
  },
  {
    "id_pessoas": 472,
    "nome_pessoa": "MATHEUS HENRIQUE LOURENCO CAMPOS",
    "departamento": "TI - ERP"
  },
  {
    "id_pessoas": 352,
    "nome_pessoa": "MATILDES PEREIRA BORGES E SILVA",
    "departamento": "DEPARTAMENTO PESSOAL"
  },
  {
    "id_pessoas": 2763,
    "nome_pessoa": "MAURO CAMPOS THIBAU",
    "departamento": "LOGISTICA"
  },
  {
    "id_pessoas": 2900,
    "nome_pessoa": "MAURO LANE DE OLIVEIRA",
    "departamento": "TI - CENTRAL DE SERVICOS"
  },
  {
    "id_pessoas": 1410,
    "nome_pessoa": "MERIAN SOUZA LOPES",
    "departamento": "ASSESSORIA CONTABIL"
  },
  {
    "id_pessoas": 2882,
    "nome_pessoa": "MICAELA RIBEIRO ARAUJO",
    "departamento": "FILIAL 002"
  },
  {
    "id_pessoas": 2325,
    "nome_pessoa": "MICHELE DE CARVALHO MARTINS",
    "departamento": "SOLUCOES ECONOMICAS"
  },
  {
    "id_pessoas": 173,
    "nome_pessoa": "MICHELLE APARECIDA RIBEIRO",
    "departamento": "TI - GERE?NCIA"
  },
  {
    "id_pessoas": 312,
    "nome_pessoa": "MICHELLE ARESLAINE DE FARIA",
    "departamento": "AUDITORIA INTERNA"
  },
  {
    "id_pessoas": 2327,
    "nome_pessoa": "MIKAELA DA SILVA BORGES SERRANO",
    "departamento": "CREDITO E COBRANCA"
  },
  {
    "id_pessoas": 89,
    "nome_pessoa": "MIKAELLA SILVA SANTANA",
    "departamento": "FILIAL 002"
  },
  {
    "id_pessoas": 1411,
    "nome_pessoa": "MILENA APARECIDA BRAGA DE OLIVEIRA",
    "departamento": "OBRAS E ENGENHARIA"
  },
  {
    "id_pessoas": 2312,
    "nome_pessoa": "MILIANY CINTHIA MARTINS DO CARMO",
    "departamento": "FINANCEIRO"
  },
  {
    "id_pessoas": 660,
    "nome_pessoa": "MIRELA CAETANO",
    "departamento": "OPERACOES DE CREDITO"
  },
  {
    "id_pessoas": 2121,
    "nome_pessoa": "NATALI FERNANDA DE JESUS GUNDIM",
    "departamento": "OVERHEAD - OUVIDORIA"
  },
  {
    "id_pessoas": 1678,
    "nome_pessoa": "NATALIA BORGES RODRIGUES",
    "departamento": "OVERHEAD - CONTROLES INTERNOS"
  },
  {
    "id_pessoas": 2716,
    "nome_pessoa": "NATALIA VIEIRA MELO",
    "departamento": "FINANCEIRO"
  },
  {
    "id_pessoas": 136,
    "nome_pessoa": "NATHALIA APARECIDA DA SILVA",
    "departamento": "MARKETING"
  },
  {
    "id_pessoas": 2875,
    "nome_pessoa": "NATHALIA CARDOSO TEIXEIRA",
    "departamento": "PLANEJAMENTO ECONOMICO E FINANCEIRO"
  },
  {
    "id_pessoas": 2239,
    "nome_pessoa": "NATHALIA GIOVANA BORGES",
    "departamento": "ATENDIMENTO"
  },
  {
    "id_pessoas": 2647,
    "nome_pessoa": "NAYARA PIRES LIMA GOZZI",
    "departamento": "OPERACOES DE CREDITO"
  },
  {
    "id_pessoas": 399,
    "nome_pessoa": "NEILA NESRALA VALE CASTILHO",
    "departamento": "SECRETARIA"
  },
  {
    "id_pessoas": 663,
    "nome_pessoa": "NICOLLAS SANTOS SILVA",
    "departamento": "OPERACOES DE CREDITO"
  },
  {
    "id_pessoas": 2784,
    "nome_pessoa": "NICOLY KETLIN DOS REIS",
    "departamento": "SOLUCOES ECONOMICAS"
  },
  {
    "id_pessoas": 480,
    "nome_pessoa": "NIVIA MARIA REIS MATEUS",
    "departamento": "TI - ADMINISTRATIVO"
  },
  {
    "id_pessoas": 2409,
    "nome_pessoa": "NYCOLAS BORGES DE CARVALHO",
    "departamento": "TI - DESENVOLVIMENTO"
  },
  {
    "id_pessoas": 991,
    "nome_pessoa": "PAMELA SOUZA PEREIRA",
    "departamento": "CENTRO DE DISTRIBUICAO GERAL"
  },
  {
    "id_pessoas": 458,
    "nome_pessoa": "PAOLA BASTOS DE OLIVEIRA",
    "departamento": "AUDITORIA INTERNA"
  },
  {
    "id_pessoas": 175,
    "nome_pessoa": "PATRICIA ALINE FRANCISCO DE SOUZA",
    "departamento": "LOGISTICA"
  },
  {
    "id_pessoas": 241,
    "nome_pessoa": "PATRICIA ALVES DE MORAES",
    "departamento": "ASSESSORIA FISCAL"
  },
  {
    "id_pessoas": 721,
    "nome_pessoa": "PATRICIA GABRIELE CORTES SILVA MOTA",
    "departamento": "OUVIDORIA"
  },
  {
    "id_pessoas": 1989,
    "nome_pessoa": "PAULO VICTOR DE SOUZA",
    "departamento": "TI - CENTRAL DE SERVICOS"
  },
  {
    "id_pessoas": 2766,
    "nome_pessoa": "PEDRO AUGUSTO AMARAL",
    "departamento": "OVERHEAD - PRODUTOS BANCARIOS"
  },
  {
    "id_pessoas": 2473,
    "nome_pessoa": "POLIANA LOURDES DE OLIVEIRA SILVA",
    "departamento": "PROJETO MEMORIA Z"
  },
  {
    "id_pessoas": 445,
    "nome_pessoa": "POLLYANE RODRIGUES FERNANDES",
    "departamento": "TI ERP 2"
  },
  {
    "id_pessoas": 307,
    "nome_pessoa": "POLYANA ABADIA ALVES",
    "departamento": "DEPARTAMENTO PESSOAL"
  },
  {
    "id_pessoas": 1917,
    "nome_pessoa": "PRISCILA ALQUINO CAMPOS",
    "departamento": "COMERCIAL BACKOFFICE"
  },
  {
    "id_pessoas": 2767,
    "nome_pessoa": "RAFAEL DE CASTRO BORGES",
    "departamento": "OVERHEAD - RISCOS FINANCEIROS"
  },
  {
    "id_pessoas": 2708,
    "nome_pessoa": "RAFAEL SOARES CARDOSO",
    "departamento": "TI - ERP"
  },
  {
    "id_pessoas": 508,
    "nome_pessoa": "RAFAELA DE PAULA RODRIGUES",
    "departamento": "E-COMMERCE"
  },
  {
    "id_pessoas": 1412,
    "nome_pessoa": "RAIANE PEREIRA TEODORO GONCALVES",
    "departamento": "OPERACOES DE CREDITO"
  },
  {
    "id_pessoas": 505,
    "nome_pessoa": "RENATA APARECIDA SALES DE OLIVEIRA",
    "departamento": "E-COMMERCE"
  },
  {
    "id_pessoas": 280,
    "nome_pessoa": "RENATA ISABEL RIBEIRO",
    "departamento": "COMPRAS"
  },
  {
    "id_pessoas": 127,
    "nome_pessoa": "RINALDO MIRANDA BAIA",
    "departamento": "COMPRAS"
  },
  {
    "id_pessoas": 1022,
    "nome_pessoa": "ROBERT LEON SOUZA RODRIGUES",
    "departamento": "TI - CENTRAL DE SERVICOS"
  },
  {
    "id_pessoas": 453,
    "nome_pessoa": "ROBERTA AUXILIADORA ALVES",
    "departamento": "ASSESSORIA FISCAL"
  },
  {
    "id_pessoas": 451,
    "nome_pessoa": "RODRIGO JANUARIO",
    "departamento": "TI - GERE?NCIA"
  },
  {
    "id_pessoas": 665,
    "nome_pessoa": "ROGERIO SANTOS FRANCA DE JESUS",
    "departamento": "CREDITO E COBRANCA"
  },
  {
    "id_pessoas": 611,
    "nome_pessoa": "ROMERO ZEMA",
    "departamento": "PRESIDENTE"
  },
  {
    "id_pessoas": 2125,
    "nome_pessoa": "ROMERO ZEMA JUNIOR",
    "departamento": "EXPANSAO (NOVAS FILIAIS)"
  },
  {
    "id_pessoas": 397,
    "nome_pessoa": "RONY MARTINS VIDA FILHO",
    "departamento": "LOGISTICA"
  },
  {
    "id_pessoas": 1688,
    "nome_pessoa": "ROSANA APARECIDA EUSTAQUIA SILVA",
    "departamento": "AUDITORIA INTERNA"
  },
  {
    "id_pessoas": 398,
    "nome_pessoa": "ROSELYANE JOYCE CAMPOS ALVARES",
    "departamento": "CENTRAL DE QUALIDADE"
  },
  {
    "id_pessoas": 259,
    "nome_pessoa": "RULLER ROBERTO VIEIRA",
    "departamento": "TRANSPORTE"
  },
  {
    "id_pessoas": 1663,
    "nome_pessoa": "SABRINA GABRIELA APARECIDA COSTA CAETANO",
    "departamento": "SOLUCOES ECONOMICAS"
  },
  {
    "id_pessoas": 348,
    "nome_pessoa": "SABRINA SILVA AMARAL",
    "departamento": "COMPRAS"
  },
  {
    "id_pessoas": 2830,
    "nome_pessoa": "SAFIRA DE BRITO OLIVEIRA",
    "departamento": "CADASTRO"
  },
  {
    "id_pessoas": 1527,
    "nome_pessoa": "SAMELLA STEFANI SILVA RAMOS",
    "departamento": "TI - CENTRAL DE SERVICOS"
  },
  {
    "id_pessoas": 500,
    "nome_pessoa": "SAMUEL CARDOSO MARCELINO",
    "departamento": "TI - DESENVOLVIMENTO"
  },
  {
    "id_pessoas": 2326,
    "nome_pessoa": "SAMUEL FERNANDES RODRIGUES",
    "departamento": "SOLUCOES ECONOMICAS"
  },
  {
    "id_pessoas": 2149,
    "nome_pessoa": "SAMUEL LEANDRO DE SOUZA GONCALVES",
    "departamento": "LOGISTICA"
  },
  {
    "id_pessoas": 233,
    "nome_pessoa": "SAMUEL MENEZES BORGES",
    "departamento": "TI - CENTRAL DE SERVICOS"
  },
  {
    "id_pessoas": 163,
    "nome_pessoa": "SANDRA CRISTINA FERREIRA CORREIA",
    "departamento": "MANUTENCAO 2"
  },
  {
    "id_pessoas": 932,
    "nome_pessoa": "SARA WINTER FERREIRA",
    "departamento": "E-COMMERCE"
  },
  {
    "id_pessoas": 1991,
    "nome_pessoa": "SAVIO ALESSANDRO CARDOSO",
    "departamento": "TI - GERE?NCIA"
  },
  {
    "id_pessoas": 167,
    "nome_pessoa": "SEBASTIAO SOUZA BARRETO",
    "departamento": "LOGISTICA"
  },
  {
    "id_pessoas": 2804,
    "nome_pessoa": "STEFANI MARIANE DA CRUZ",
    "departamento": "TI - GERE?NCIA"
  },
  {
    "id_pessoas": 483,
    "nome_pessoa": "STEFANY VICENTE PEREIRA",
    "departamento": "MARKETING"
  },
  {
    "id_pessoas": 714,
    "nome_pessoa": "SUELLEM APARECIDA BORGES TEIXEIRA",
    "departamento": "OVERHEAD - AUDITORIA INTERNA"
  },
  {
    "id_pessoas": 667,
    "nome_pessoa": "SUELY MARTINS PEREIRA DOS REIS",
    "departamento": "OPERACOES DE CREDITO"
  },
  {
    "id_pessoas": 2419,
    "nome_pessoa": "TALITA RAFAELA DA COSTA",
    "departamento": "OVERHEAD - B.OFF TESOURARIA"
  },
  {
    "id_pessoas": 2992,
    "nome_pessoa": "TALITA VALLE DE CASTRO",
    "departamento": "CENTRO DE DISTRIBUICAO GERAL"
  },
  {
    "id_pessoas": 719,
    "nome_pessoa": "TALLES HENRIQUE OLIVEIRA",
    "departamento": "GERENCIA COMERCIAL"
  },
  {
    "id_pessoas": 1937,
    "nome_pessoa": "TATIANE OLIVEIRA DE SOUZA MILAGRES",
    "departamento": "MARKETING"
  },
  {
    "id_pessoas": 402,
    "nome_pessoa": "TAUANE DAS GRACAS DE ALMEIDA",
    "departamento": "DEPARTAMENTO PESSOAL"
  },
  {
    "id_pessoas": 271,
    "nome_pessoa": "TELMA GRAZIELA MATEUS FERREIRA",
    "departamento": "FINANCEIRO"
  },
  {
    "id_pessoas": 2173,
    "nome_pessoa": "THAIS SANTOS CUNHA",
    "departamento": "CONTEMPLACAO"
  },
  {
    "id_pessoas": 614,
    "nome_pessoa": "THAIS SEVERINO DE SOUSA",
    "departamento": "CENTRO DE DISTRIBUICAO GERAL"
  },
  {
    "id_pessoas": 1423,
    "nome_pessoa": "THAIZA CRISTINI DA SILVA",
    "departamento": "FINANCEIRO"
  },
  {
    "id_pessoas": 2413,
    "nome_pessoa": "THAIZZA GONCALVES SILVA",
    "departamento": "FINANCEIRO"
  },
  {
    "id_pessoas": 2129,
    "nome_pessoa": "THAYNA VITORIA VIEIRA SILVA",
    "departamento": "CENTRO DE DISTRIBUICAO GERAL"
  },
  {
    "id_pessoas": 214,
    "nome_pessoa": "THAYNARA CRISTINA DE OLIVEIRA",
    "departamento": "FINANCEIRO"
  },
  {
    "id_pessoas": 177,
    "nome_pessoa": "THIERS VAZ DA SILVA",
    "departamento": "LOGISTICA"
  },
  {
    "id_pessoas": 354,
    "nome_pessoa": "VALDINEI FERREIRA DE ALMEIDA",
    "departamento": "LOGISTICA"
  },
  {
    "id_pessoas": 244,
    "nome_pessoa": "VALERIA LUCIA DA SILVA",
    "departamento": "DEPARTAMENTO PESSOAL"
  },
  {
    "id_pessoas": 264,
    "nome_pessoa": "VALTER JOAQUIM PEREIRA JUNIOR",
    "departamento": "JURIDICO"
  },
  {
    "id_pessoas": 1413,
    "nome_pessoa": "VANDERLEIA CRISTINA LAZARO",
    "departamento": "CREDITO E COBRANCA"
  },
  {
    "id_pessoas": 71,
    "nome_pessoa": "VANESSA ALVES DA SILVA",
    "departamento": "ALIENACAO"
  },
  {
    "id_pessoas": 715,
    "nome_pessoa": "VANESSA CARDOSO TEIXEIRA",
    "departamento": "OVERHEAD - PRODUTOS BANCARIOS"
  },
  {
    "id_pessoas": 724,
    "nome_pessoa": "VANESSA FURTADO PAIM",
    "departamento": "SAC"
  },
  {
    "id_pessoas": 375,
    "nome_pessoa": "VANESSA RODRIGUES DO PRADO",
    "departamento": "PLANEJAMENTO ECONOMICO E FINANCEIRO"
  },
  {
    "id_pessoas": 74,
    "nome_pessoa": "VANESSA SOUZA BARBOSA",
    "departamento": "JURIDICO"
  },
  {
    "id_pessoas": 442,
    "nome_pessoa": "VANUSA FERREIRA CARDOSO",
    "departamento": "FINANCEIRO"
  },
  {
    "id_pessoas": 971,
    "nome_pessoa": "VEBER RENATO DE ANDRADE JUNIOR",
    "departamento": "AUDITORIA INTERNA"
  },
  {
    "id_pessoas": 2606,
    "nome_pessoa": "VICTOR LUIS LUFT",
    "departamento": "OVERHEAD - CRED. E INDICADORES"
  },
  {
    "id_pessoas": 437,
    "nome_pessoa": "VINICIUS GOMES CORREIA",
    "departamento": "GESTAO INTEGRADA ZEMA"
  },
  {
    "id_pessoas": 486,
    "nome_pessoa": "VITOR HUGO DE MORAIS",
    "departamento": "TI - ERP"
  },
  {
    "id_pessoas": 438,
    "nome_pessoa": "VITOR HUGO DE SOUZA MORAIS",
    "departamento": "TI - ERP"
  },
  {
    "id_pessoas": 364,
    "nome_pessoa": "VITORIA DE OLIVEIRA SILVA",
    "departamento": "COMPRAS"
  },
  {
    "id_pessoas": 1445,
    "nome_pessoa": "WANDERSON BRUNO DO NASCIMENTO OLIVEIRA",
    "departamento": "LOGISTICA"
  },
  {
    "id_pessoas": 510,
    "nome_pessoa": "WEMERSON DIAS DOS SANTOS",
    "departamento": "E-COMMERCE"
  },
  {
    "id_pessoas": 1023,
    "nome_pessoa": "WENDER DAVID ELIAS BORGES",
    "departamento": "TI - CENTRAL DE SERVICOS"
  },
  {
    "id_pessoas": 1794,
    "nome_pessoa": "WILKER HEBERT DE OLIVEIRA LIMA",
    "departamento": "OVERHEAD - Canal - Eletrozema"
  },
  {
    "id_pessoas": 2785,
    "nome_pessoa": "WILKER SANTIAGO DE CASTRO ROSA",
    "departamento": "OVERHEAD - Canal - Eletrozema"
  },
  {
    "id_pessoas": 185,
    "nome_pessoa": "WILLIAM JORGE DE PAULA JUNIOR",
    "departamento": "TI - SOFTWARE"
  },
  {
    "id_pessoas": 286,
    "nome_pessoa": "WILSON PEREIRA DA SILVA FILHO",
    "departamento": "LOGISTICA"
  },
  {
    "id_pessoas": 1816,
    "nome_pessoa": "WILTON JOSE MAGALHAES JUNIOR",
    "departamento": "TI - CENTRAL DE SERVICOS"
  },
  {
    "id_pessoas": 1435,
    "nome_pessoa": "YSADORA CANDIDO CAMPOS",
    "departamento": "CADASTRO"
  },
  {
    "id_pessoas": 718,
    "nome_pessoa": "YURI JIVAGO DIAS ALVES",
    "departamento": "OVERHEAD - ADMINISTRATIVO"
  },
  {
    "id_pessoas": 2769,
    "nome_pessoa": "ADELIA PEREIRA DA SILVA",
    "departamento": "TERCEIRO"
  },
  {
    "id_pessoas": 2827,
    "nome_pessoa": "ADRIAN DORNELAS MACHADO",
    "departamento": "TERCEIRO"
  },
  {
    "id_pessoas": 2996,
    "nome_pessoa": "ALESSANDRO VAZ MACHADO",
    "departamento": "TERCEIRO"
  },
  {
    "id_pessoas": 2859,
    "nome_pessoa": "ALEXANDRE DOMINGOS GOMES",
    "departamento": "TERCEIRO"
  },
  {
    "id_pessoas": 2990,
    "nome_pessoa": "ALINE AUGUSTA FONSECA",
    "departamento": "TERCEIRO"
  },
  {
    "id_pessoas": 2286,
    "nome_pessoa": "ANDRESSA OLIVEIRA SILVA ANDRADE",
    "departamento": "TERCEIRO"
  },
  {
    "id_pessoas": 2684,
    "nome_pessoa": "ANGELINA FERREIRA DA SILVA",
    "departamento": "TERCEIRO"
  },
  {
    "id_pessoas": 1223,
    "nome_pessoa": "ANTONIO EDSON FERREIRA CLEMENTINO",
    "departamento": "TERCEIRO"
  },
  {
    "id_pessoas": 1780,
    "nome_pessoa": "ANTONIO GILBERTO DA SILVA MARINHO",
    "departamento": "TERCEIRO"
  },
  {
    "id_pessoas": 2266,
    "nome_pessoa": "ANTONIO GILSEMBERG SOUZA PINHEIRO",
    "departamento": "TERCEIRO"
  },
  {
    "id_pessoas": 2788,
    "nome_pessoa": "AUANY CRISTINA SILVA VIEIRA",
    "departamento": "TERCEIRO"
  },
  {
    "id_pessoas": 2775,
    "nome_pessoa": "AUGUSTO ROBERTO GONCALVES",
    "departamento": "TERCEIRO"
  },
  {
    "id_pessoas": 765,
    "nome_pessoa": "BARBARA MATILDE DE OLIVEIRA",
    "departamento": "TERCEIRO"
  },
  {
    "id_pessoas": 766,
    "nome_pessoa": "BENIVALDO FERREIRA DOS SANTOS",
    "departamento": "TERCEIRO"
  },
  {
    "id_pessoas": 2398,
    "nome_pessoa": "BRENO SANTANA SILVA",
    "departamento": "TERCEIRO"
  },
  {
    "id_pessoas": 1607,
    "nome_pessoa": "BRUNA CRISTINA SILVA",
    "departamento": "TERCEIRO"
  },
  {
    "id_pessoas": 2781,
    "nome_pessoa": "BRUNO RAFAEL MARTINS",
    "departamento": "TERCEIRO"
  },
  {
    "id_pessoas": 2857,
    "nome_pessoa": "CARLOS DANIEL EUGENIO",
    "departamento": "TERCEIRO"
  },
  {
    "id_pessoas": 2209,
    "nome_pessoa": "CARLOS HENRIQUE SOARES DE JESUS",
    "departamento": "TERCEIRO"
  },
  {
    "id_pessoas": 2555,
    "nome_pessoa": "CICERO FABIO GRIGORIO DOS SANTOS",
    "departamento": "TERCEIRO"
  },
  {
    "id_pessoas": 775,
    "nome_pessoa": "CICERO MARCELIO BENTO DE SOUZA SILVA",
    "departamento": "TERCEIRO"
  },
  {
    "id_pessoas": 2905,
    "nome_pessoa": "CLAUDENI SOUZA",
    "departamento": "PRESTADOR"
  },
  {
    "id_pessoas": 779,
    "nome_pessoa": "CLEBER RODRIGUES OLVEIRA",
    "departamento": "TERCEIRO"
  },
  {
    "id_pessoas": 2354,
    "nome_pessoa": "CRISTIANA RAMOS RODRIGUES",
    "departamento": "PRESTADOR"
  },
  {
    "id_pessoas": 2851,
    "nome_pessoa": "DANIELA PATRICIO DE OLIVEIRA",
    "departamento": "TERCEIRO"
  },
  {
    "id_pessoas": 784,
    "nome_pessoa": "DAVID MOREIRA DA CRUZ",
    "departamento": "TERCEIRO"
  },
  {
    "id_pessoas": 2298,
    "nome_pessoa": "DENILSON NASCIMENTO DOS SANTOS",
    "departamento": "TERCEIRO"
  },
  {
    "id_pessoas": 2391,
    "nome_pessoa": "DOUGLAS GIOVANI MESSIAS",
    "departamento": "TERCEIRO"
  },
  {
    "id_pessoas": 1485,
    "nome_pessoa": "EDIRCEU HENRIQUE DO PORTO",
    "departamento": "TERCEIRO"
  },
  {
    "id_pessoas": 2329,
    "nome_pessoa": "EDSON VICENTE CAETANO",
    "departamento": "TERCEIRO"
  },
  {
    "id_pessoas": 2687,
    "nome_pessoa": "EDUARDO DOS REIS SILVA",
    "departamento": "TERCEIRO"
  },
  {
    "id_pessoas": 791,
    "nome_pessoa": "EDUARDO MARTINS",
    "departamento": "TERCEIRO"
  },
  {
    "id_pessoas": 795,
    "nome_pessoa": "ERMANES DE LIMA ARAUJO",
    "departamento": "TERCEIRO"
  },
  {
    "id_pessoas": 798,
    "nome_pessoa": "FABIANO CESAR DIAS GASPAR",
    "departamento": "TERCEIRO"
  },
  {
    "id_pessoas": 1600,
    "nome_pessoa": "FABIO DE SOUZA DA CRUZ",
    "departamento": "TERCEIRO"
  },
  {
    "id_pessoas": 2669,
    "nome_pessoa": "FABRICIO MANOEL DE CASTRO",
    "departamento": "TERCEIRO"
  },
  {
    "id_pessoas": 972,
    "nome_pessoa": "FELIX SANTOS PINTO",
    "departamento": "PRESTADOR"
  },
  {
    "id_pessoas": 2903,
    "nome_pessoa": "FERNANDO HENRIQUE MARTINS",
    "departamento": "TERCEIRO"
  },
  {
    "id_pessoas": 2483,
    "nome_pessoa": "FLAVIO AUGUSTO LAERT",
    "departamento": "TERCEIRO"
  },
  {
    "id_pessoas": 1647,
    "nome_pessoa": "FLAVIO CESAR VAZ REIS",
    "departamento": "TERCEIRO"
  },
  {
    "id_pessoas": 964,
    "nome_pessoa": "FLAVIO VITOR AMARAL",
    "departamento": "TERCEIRO"
  },
  {
    "id_pessoas": 806,
    "nome_pessoa": "FRANCISCO DE ASSIS DE OLIVEIRA",
    "departamento": "TERCEIRO"
  },
  {
    "id_pessoas": 2153,
    "nome_pessoa": "FRANCISCO JAMERSON LIMA TOMAS",
    "departamento": "TERCEIRO"
  },
  {
    "id_pessoas": 2375,
    "nome_pessoa": "GABRIEL DE SOUSA GOMES",
    "departamento": "TERCEIRO"
  },
  {
    "id_pessoas": 2835,
    "nome_pessoa": "GILSON FRANCISCO DE AMORIM",
    "departamento": "PRESTADOR"
  },
  {
    "id_pessoas": 2711,
    "nome_pessoa": "IRAILTON MOURA SOUZA",
    "departamento": "TERCEIRO"
  },
  {
    "id_pessoas": 2569,
    "nome_pessoa": "ISABELE MESQUITA VALLE MACEDO",
    "departamento": "PRESTADOR"
  },
  {
    "id_pessoas": 2695,
    "nome_pessoa": "ISMAEL MORAES NUNES",
    "departamento": "TERCEIRO"
  },
  {
    "id_pessoas": 817,
    "nome_pessoa": "JADSON ANDRE ROSARIO MUNIZ",
    "departamento": "TERCEIRO"
  },
  {
    "id_pessoas": 2268,
    "nome_pessoa": "JEAN DIAS SILVA",
    "departamento": "TERCEIRO"
  },
  {
    "id_pessoas": 2924,
    "nome_pessoa": "JOAO PEDRO FERREIRA MAIA",
    "departamento": "PRESTADOR"
  },
  {
    "id_pessoas": 2786,
    "nome_pessoa": "JOAO VICTOR LIMA DE ANDRADE",
    "departamento": "PRESTADOR"
  },
  {
    "id_pessoas": 2712,
    "nome_pessoa": "JONAS DAVID SOARES DA CRUZ",
    "departamento": "TERCEIRO"
  },
  {
    "id_pessoas": 2879,
    "nome_pessoa": "JONAX FRANCISCO D OLIVEIRA",
    "departamento": "TERCEIRO"
  },
  {
    "id_pessoas": 831,
    "nome_pessoa": "JOSE FLAVIO BERNABE DOS SANTOS",
    "departamento": "TERCEIRO"
  },
  {
    "id_pessoas": 2280,
    "nome_pessoa": "JOSE THIAGO DA SILVA",
    "departamento": "TERCEIRO"
  },
  {
    "id_pessoas": 2100,
    "nome_pessoa": "JOSE WILLIAMS RIBEIRO DA SILVA LIMA",
    "departamento": "TERCEIRO"
  },
  {
    "id_pessoas": 2791,
    "nome_pessoa": "JUCELINO SILVA DE ALMEIDA",
    "departamento": "TERCEIRO"
  },
  {
    "id_pessoas": 2159,
    "nome_pessoa": "JULIO CESAR DE SOUZA SOARES",
    "departamento": "TERCEIRO"
  },
  {
    "id_pessoas": 2860,
    "nome_pessoa": "KEVELYN MARQUES OLIVEIRA",
    "departamento": "TERCEIRO"
  },
  {
    "id_pessoas": 2691,
    "nome_pessoa": "KLEBER CONCEICAO DESIDERIO",
    "departamento": "TERCEIRO"
  },
  {
    "id_pessoas": 2660,
    "nome_pessoa": "LEANDRO DA SILVA RODRIGUES",
    "departamento": "TERCEIRO"
  },
  {
    "id_pessoas": 2792,
    "nome_pessoa": "LEUDIMAR BARBOSA DA SILVA",
    "departamento": "TERCEIRO"
  },
  {
    "id_pessoas": 2776,
    "nome_pessoa": "LUCAS ALCANTARA DA LUZ",
    "departamento": "TERCEIRO"
  },
  {
    "id_pessoas": 851,
    "nome_pessoa": "LUCAS DANIEL FELIX",
    "departamento": "TERCEIRO"
  },
  {
    "id_pessoas": 2855,
    "nome_pessoa": "LUCAS SILVA ALVES",
    "departamento": "TERCEIRO"
  },
  {
    "id_pessoas": 1486,
    "nome_pessoa": "LUIZ GUSTAVO DA CRUZ",
    "departamento": "TERCEIRO"
  },
  {
    "id_pessoas": 2997,
    "nome_pessoa": "LUIZ GUSTAVO VALERIANO ALVES",
    "departamento": "TERCEIRO"
  },
  {
    "id_pessoas": 2154,
    "nome_pessoa": "MAICON ANTONIO FERREIRA",
    "departamento": "TERCEIRO"
  },
  {
    "id_pessoas": 2258,
    "nome_pessoa": "MAICON VITOR DOS SANTOS",
    "departamento": "TERCEIRO"
  },
  {
    "id_pessoas": 2512,
    "nome_pessoa": "MAISA TAMARA DE OLIVEIRA BALDUINO",
    "departamento": "TERCEIRO"
  },
  {
    "id_pessoas": 1335,
    "nome_pessoa": "MARCELA CRISTINA BENEDITO",
    "departamento": "TERCEIRO"
  },
  {
    "id_pessoas": 1398,
    "nome_pessoa": "MARCOS ALEXANDRE CARNEIRO",
    "departamento": "PRESTADOR"
  },
  {
    "id_pessoas": 2682,
    "nome_pessoa": "MARCOS PAULO DOS SANTOS",
    "departamento": "TERCEIRO"
  },
  {
    "id_pessoas": 867,
    "nome_pessoa": "MARIA DAS GRACAS TOMAZ DE ARAUJO",
    "departamento": "TERCEIRO"
  },
  {
    "id_pessoas": 875,
    "nome_pessoa": "MURILO CELIO DA CRUZ",
    "departamento": "TERCEIRO"
  },
  {
    "id_pessoas": 2732,
    "nome_pessoa": "NATHAN MAKONY DE LIMA",
    "departamento": "TERCEIRO"
  },
  {
    "id_pessoas": 2429,
    "nome_pessoa": "PAULO JUNIOR LIRA DOS SANTOS",
    "departamento": "TERCEIRO"
  },
  {
    "id_pessoas": 885,
    "nome_pessoa": "PEDRO HENRIQUE DE SOUZA ALVES",
    "departamento": "TERCEIRO"
  },
  {
    "id_pessoas": 2780,
    "nome_pessoa": "RAFAEL FILIPE DO CARMO",
    "departamento": "TERCEIRO"
  },
  {
    "id_pessoas": 2850,
    "nome_pessoa": "RAFAEL RODRIGUES ALVES LUCIO",
    "departamento": "TERCEIRO"
  },
  {
    "id_pessoas": 1467,
    "nome_pessoa": "RAFAELA JORDANA DE OLIVEIRA",
    "departamento": "TERCEIRO"
  },
  {
    "id_pessoas": 2252,
    "nome_pessoa": "RAIMUNDO NONATO MENDES CRUZ",
    "departamento": "TERCEIRO"
  },
  {
    "id_pessoas": 2300,
    "nome_pessoa": "RANDER VINICIUS IZAQUE",
    "departamento": "TERCEIRO"
  },
  {
    "id_pessoas": 1682,
    "nome_pessoa": "ROBSON FRANCISCO DOS SANTOS",
    "departamento": "TERCEIRO"
  },
  {
    "id_pessoas": 2998,
    "nome_pessoa": "SABRINA RIBEIRO DE ALMEIDA",
    "departamento": "TERCEIRO"
  },
  {
    "id_pessoas": 2031,
    "nome_pessoa": "SAMARA RIBEIRO ALMEIDA",
    "departamento": "TERCEIRO"
  },
  {
    "id_pessoas": 2743,
    "nome_pessoa": "STEFANY CRISTINA DOS SANTOS",
    "departamento": "TERCEIRO"
  },
  {
    "id_pessoas": 2787,
    "nome_pessoa": "THAYSLAN LIMA DE CARVALHO",
    "departamento": "TERCEIRO"
  },
  {
    "id_pessoas": 2513,
    "nome_pessoa": "TIAGO MORAIS PAULA",
    "departamento": "TERCEIRO"
  },
  {
    "id_pessoas": 2849,
    "nome_pessoa": "VALDEMIR DOS REIS INOCENCIO",
    "departamento": "TERCEIRO"
  },
  {
    "id_pessoas": 911,
    "nome_pessoa": "VITOR HUGO RIBEIRO CAETANO",
    "departamento": "TERCEIRO"
  },
  {
    "id_pessoas": 2733,
    "nome_pessoa": "WEBERSOM EURIPEDES GONDIM",
    "departamento": "TERCEIRO"
  },
  {
    "id_pessoas": 916,
    "nome_pessoa": "WESDIRLEY ALVES",
    "departamento": "TERCEIRO"
  },
  {
    "id_pessoas": 2779,
    "nome_pessoa": "WEVERTON RUAN DA SILVA",
    "departamento": "TERCEIRO"
  },
  {
    "id_pessoas": 919,
    "nome_pessoa": "WILLIAN FERNANDO DA SILVA",
    "departamento": "TERCEIRO"
  },
  {
    "id_pessoas": 2692,
    "nome_pessoa": "ZE AMILTOM DE SOUZA CRUZ",
    "departamento": "TERCEIRO"
  }
]